adafruit_tlv493d.py
adafruit_circuitpython_tlv493d-2.0.10.dist-info/licenses/LICENSE
adafruit_circuitpython_tlv493d-2.0.10.dist-info/METADATA
adafruit_circuitpython_tlv493d-2.0.10.dist-info/WHEEL
adafruit_circuitpython_tlv493d-2.0.10.dist-info/top_level.txt
adafruit_circuitpython_tlv493d-2.0.10.dist-info/RECORD
