Metadata-Version: 2.4
Name: adafruit-circuitpython-tlv493d
Version: 2.0.10
Summary: CircuitPython helper library for the TLV493D 3-axis magnetometer
Author-email: Adafruit Industries <circuitpython@adafruit.com>
License: MIT
Project-URL: Homepage, https://github.com/adafruit/Adafruit_CircuitPython_TLV493D
Keywords: adafruit,blinka,circuitpython,micropython,tlv493d,tlv,sensor,magnetometer
Classifier: Intended Audience :: Developers
Classifier: Topic :: Software Development :: Libraries
Classifier: Topic :: Software Development :: Embedded Systems
Classifier: Topic :: System :: Hardware
Classifier: License :: OSI Approved :: MIT License
Classifier: Programming Language :: Python :: 3
License-File: LICENSE
Requires-Dist: Adafruit-Blinka
Requires-Dist: adafruit-circuitpython-register
Requires-Dist: adafruit-circuitpython-busdevice
Provides-Extra: optional
Dynamic: license-file
